LICENSE
MANIFEST.in
README.rst
setup.py
django_epiced.egg-info/PKG-INFO
django_epiced.egg-info/SOURCES.txt
django_epiced.egg-info/dependency_links.txt
django_epiced.egg-info/requires.txt
django_epiced.egg-info/top_level.txt
epiced/__init__.py
epiced/fields.py
epiced/models.py
epiced/tests.py
epiced/views.py
epiced/widgets.py
epiced/static/epiced/images/edit.png
epiced/static/epiced/images/fullscreen.png
epiced/static/epiced/images/preview.png
epiced/static/epiced/js/epiceditor.js
epiced/static/epiced/js/epiceditor.min.js
epiced/static/epiced/themes/base/epiceditor.css
epiced/static/epiced/themes/editor/epic-dark.css
epiced/static/epiced/themes/editor/epic-light.css
epiced/static/epiced/themes/preview/bartik.css
epiced/static/epiced/themes/preview/github.css
epiced/static/epiced/themes/preview/preview-dark.css
epiced/templates/epiced/widget.html