Metadata-Version: 1.1
Name: django-epiced
Version: 0.3.1
Summary: A Django app to add the EpicEditor with easy to use widget.
Home-page: https://github.com/belug23/django-epiced
Author: Belug
Author-email: belug@oss.cx
License: BSD License
Platform: UNKNOWN
Classifier: Environment :: Web Environment
Classifier: Framework :: Django
Classifier: Intended Audience :: Developers
Classifier: License :: OSI Approved :: BSD License
Classifier: Operating System :: OS Independent
Classifier: Programming Language :: Python
Classifier: Programming Language :: Python :: 2.6
Classifier: Programming Language :: Python :: 2.7
Classifier: Topic :: Internet :: WWW/HTTP
Classifier: Topic :: Internet :: WWW/HTTP :: Dynamic Content
Classifier: Topic :: Text Editors
